nice_cut/__init__.py
nice_cut/argument_parser.py
nice_cut/info.py
nice_cut/main.py
nice_cut/space.py
nice_cut/version.py
nice_cut/supported_formats/__init__.py
nice_cut/supported_formats/srt.py
NiceCut-0.1.0.dist-info/LICENSE
NiceCut-0.1.0.dist-info/METADATA
NiceCut-0.1.0.dist-info/WHEEL
NiceCut-0.1.0.dist-info/entry_points.txt
NiceCut-0.1.0.dist-info/top_level.txt
NiceCut-0.1.0.dist-info/RECORD
