Metadata-Version: 2.1
Name: NiceCut
Version: 0.1.0
Summary: A tool cutting a media file into small clips according to the subtitle file
Home-page: https://github.com/nlpsuge/NiceCut
Author: nlpsuge
License: UNKNOWN
Project-URL: Bug Reports, https://github.com/nlpsuge/NiceCut/issues
Project-URL: Source, https://github.com/nlpsuge/NiceCut
Keywords: python,ffmpeg,media,python3,subtitle,srt-subtitles,cutting,english-learning
Platform: UNKNOWN
Classifier: Development Status :: 4 - Beta
Classifier: Intended Audience :: End Users/Desktop
Classifier: License :: OSI Approved :: GNU Lesser General Public License v3 or later (LGPLv3+)
Classifier: Programming Language :: Python :: 3.6
Classifier: Programming Language :: Python :: 3.7
Classifier: Programming Language :: Python :: 3.8
Classifier: Programming Language :: Python :: 3.9
Classifier: Programming Language :: Python :: 3.10
Classifier: Topic :: Desktop Environment
Classifier: Topic :: Utilities
Classifier: Topic :: Multimedia :: Video :: Conversion
Requires-Python: >=3
License-File: LICENSE
Requires-Dist: alive-progress (>=2.0.0)
